prometheux_mcp/__init__.py
prometheux_mcp/__main__.py
prometheux_mcp/client.py
prometheux_mcp/config.py
prometheux_mcp/server.py
prometheux_mcp/tools/__init__.py
prometheux_mcp-0.1.5.dist-info/licenses/LICENSE
prometheux_mcp-0.1.5.dist-info/METADATA
prometheux_mcp-0.1.5.dist-info/WHEEL
prometheux_mcp-0.1.5.dist-info/entry_points.txt
prometheux_mcp-0.1.5.dist-info/top_level.txt
prometheux_mcp-0.1.5.dist-info/RECORD
